aliyunsdkemr/__init__.py
aliyunsdkemr/endpoint.py
aliyunsdkemr/request/__init__.py
aliyunsdkemr/request/v20160408/AddClusterServiceRequest.py
aliyunsdkemr/request/v20160408/AddScalingConfigItemV2Request.py
aliyunsdkemr/request/v20160408/CloneFlowJobRequest.py
aliyunsdkemr/request/v20160408/CloneFlowRequest.py
aliyunsdkemr/request/v20160408/CreateClusterHostGroupRequest.py
aliyunsdkemr/request/v20160408/CreateClusterTemplateRequest.py
aliyunsdkemr/request/v20160408/CreateClusterV2Request.py
aliyunsdkemr/request/v20160408/CreateClusterWithTemplateRequest.py
aliyunsdkemr/request/v20160408/CreateFlowCategoryRequest.py
aliyunsdkemr/request/v20160408/CreateFlowForWebRequest.py
aliyunsdkemr/request/v20160408/CreateFlowJobRequest.py
aliyunsdkemr/request/v20160408/CreateFlowProjectClusterSettingRequest.py
aliyunsdkemr/request/v20160408/CreateFlowProjectRequest.py
aliyunsdkemr/request/v20160408/CreateFlowProjectUserRequest.py
aliyunsdkemr/request/v20160408/CreateFlowRequest.py
aliyunsdkemr/request/v20160408/CreateResourcePoolRequest.py
aliyunsdkemr/request/v20160408/CreateResourceQueueRequest.py
aliyunsdkemr/request/v20160408/CreateScalingGroupV2Request.py
aliyunsdkemr/request/v20160408/DeleteClusterTemplateRequest.py
aliyunsdkemr/request/v20160408/DeleteFlowCategoryRequest.py
aliyunsdkemr/request/v20160408/DeleteFlowJobRequest.py
aliyunsdkemr/request/v20160408/DeleteFlowProjectClusterSettingRequest.py
aliyunsdkemr/request/v20160408/DeleteFlowProjectRequest.py
aliyunsdkemr/request/v20160408/DeleteFlowProjectUserRequest.py
aliyunsdkemr/request/v20160408/DeleteFlowRequest.py
aliyunsdkemr/request/v20160408/DeleteResourcePoolRequest.py
aliyunsdkemr/request/v20160408/DeleteResourceQueueRequest.py
aliyunsdkemr/request/v20160408/DescribeClusterBasicInfoRequest.py
aliyunsdkemr/request/v20160408/DescribeClusterOperationHostTaskLogRequest.py
aliyunsdkemr/request/v20160408/DescribeClusterResourcePoolSchedulerTypeRequest.py
aliyun_python_sdk_emr-3.3.10.dist-info/LICENSE
aliyun_python_sdk_emr-3.3.10.dist-info/METADATA
aliyun_python_sdk_emr-3.3.10.dist-info/WHEEL
aliyun_python_sdk_emr-3.3.10.dist-info/top_level.txt
aliyun_python_sdk_emr-3.3.10.dist-info/RECORD
